<?xml version="1.0" encoding="UTF-8" standalone="yes" ?> 
<?xml-stylesheet href="hide-it.xsl" type="text/xsl"?>
<layoutype>fuckOFF</layoutype>

<dir>

<title>247 mov</title>

<link>https://raw.githubusercontent.com/bcrusher29/unfocused/master/xmls/247mov.xml</link>

<thumbnail></thumbnail>

<fanart></fanart>

</dir>

<dir>

<title>Due to recent events anything with eyepeetv will be removed from all my addons sorry </title>

<link>http://no_link</link>

<thumbnail></thumbnail>

<fanart></fanart>

</dir>


<dir>

<title>pluto</title>

<link>https://raw.githubusercontent.com/bcrusher29/unfocused/master/xmls/PLUTO.m3u</link>

<thumbnail></thumbnail>

<fanart></fanart>

</dir>


<title>horror</title>

<link>https://raw.githubusercontent.com/bcrusher29/unfocused/master/xmls/horror.xml</link>

<thumbnail></thumbnail>

<fanart></fanart>

</dir>

<dir>

<title>247 net</title>

<link>https://raw.githubusercontent.com/bcrusher29/unfocused/master/xmls/networks.xml</link>

<thumbnail></thumbnail>

<fanart></fanart>

</dir>

<dir>

<title>tvshows 247</title>

<link>https://raw.githubusercontent.com/bcrusher29/unfocused/master/xmls/shows247.xml</link>

<thumbnail></thumbnail>

<fanart></fanart>

</dir>


<dir>

<title>ustv247</title>

<link>https://raw.githubusercontent.com/bcrusher29/unfocused/master/xmls/ustv247.m3u</link>

<thumbnail></thumbnail>

<fanart></fanart>

</dir>
